ckanext/__init__.py
ckanext/nswdesignsystem/__init__.py
ckanext/nswdesignsystem/helpers.py
ckanext/nswdesignsystem/placeholders.py
ckanext/nswdesignsystem/plugin.py
ckanext/nswdesignsystem/types.py
ckanext/nswdesignsystem/views.py
ckanext/nswdesignsystem/assets/nswdesignsystem-script.js
ckanext/nswdesignsystem/assets/nswdesignsystem-style.css
ckanext/nswdesignsystem/assets/webassets.yml
ckanext/nswdesignsystem/assets/css/custom.css
ckanext/nswdesignsystem/assets/vendor/hljs.css
ckanext/nswdesignsystem/assets/vendor/hljs.js
ckanext/nswdesignsystem/assets/vendor/nswdesignsystem.css
ckanext/nswdesignsystem/assets/vendor/nswdesignsystem.js
ckanext/nswdesignsystem/templates/header.html
ckanext/nswdesignsystem/templates/page.html
ckanext/nswdesignsystem/templates/components/footer.html
ckanext/nswdesignsystem/templates/components/header.html
ckanext/nswdesignsystem/templates/components/main_navigation.html
ckanext/nswdesignsystem/templates/macros/_nswdesignsystem_form.html
ckanext/nswdesignsystem/templates/macros/nsw_buttons.html
ckanext/nswdesignsystem/templates/macros/nsw_links.html
ckanext/nswdesignsystem/templates/macros/nswdesignsystem/_accortion_toggle_all.html
ckanext/nswdesignsystem/templates/macros/nswdesignsystem/_footer_lower.html
ckanext/nswdesignsystem/templates/macros/nswdesignsystem/_footer_upper.html
ckanext/nswdesignsystem/templates/macros/nswdesignsystem/_footer_wrapper.html
ckanext/nswdesignsystem/templates/macros/nswdesignsystem/_header_inner.html
ckanext/nswdesignsystem/templates/macros/nswdesignsystem/_header_main.html
ckanext/nswdesignsystem/templates/macros/nswdesignsystem/_header_search_area.html
ckanext/nswdesignsystem/templates/macros/nswdesignsystem/_header_search_form.html
ckanext/nswdesignsystem/templates/macros/nswdesignsystem/_navigation_link.html
ckanext/nswdesignsystem/templates/macros/nswdesignsystem/_navigation_main.html
ckanext/nswdesignsystem/templates/macros/nswdesignsystem/_navigation_nav.html
ckanext_nswdesignsystem-0.1.8.post1.dist-info/LICENSE
ckanext_nswdesignsystem-0.1.8.post1.dist-info/METADATA
ckanext_nswdesignsystem-0.1.8.post1.dist-info/WHEEL
ckanext_nswdesignsystem-0.1.8.post1.dist-info/entry_points.txt
ckanext_nswdesignsystem-0.1.8.post1.dist-info/top_level.txt
ckanext_nswdesignsystem-0.1.8.post1.dist-info/RECORD
